pyviper/NaRnEA.py
pyviper/__init__.py
pyviper/_aziz_metacell.py
pyviper/_corr_distance.py
pyviper/_filtering_funcs.py
pyviper/_helpers_meta.py
pyviper/_metacell_funcs.py
pyviper/_pp.py
pyviper/_rep_subsample_funcs.py
pyviper/_tl.py
pyviper/_translate.py
pyviper/_viper.py
pyviper/aREA.py
pyviper/config.py
pyviper/interactome.py
pyviper/load.py
pyviper/pl.py
pyviper/pp.py
pyviper/tl.py
pyviper/_load/__init__.py
pyviper/_load/_load.py
pyviper/_load/_load_get_path.py
pyviper/_load/_load_msigdb.py
pyviper/_load/_load_regulators.py
pyviper/_load/_load_translate.py
pyviper/data/.DS_Store
pyviper/data/regulatorIDs/.DS_Store
pyviper/data/regulatorIDs/cotfs-hugo-mouse.txt
pyviper/data/regulatorIDs/cotfs-hugo.txt
pyviper/data/regulatorIDs/sig-hugo-mouse.txt
pyviper/data/regulatorIDs/sig-hugo.txt
pyviper/data/regulatorIDs/surf-hugo-mouse.txt
pyviper/data/regulatorIDs/surf-hugo.txt
pyviper/data/regulatorIDs/tfs-hugo-mouse.txt
pyviper/data/regulatorIDs/tfs-hugo.txt
pyviper/data/regulons/msigdb-c2-as-regulon.tsv
pyviper/data/regulons/msigdb-c5-as-regulon.tsv
pyviper/data/regulons/msigdb-c6-as-regulon.tsv
pyviper/data/regulons/msigdb-c7-as-regulon.tsv
pyviper/data/regulons/msigdb-h-as-regulon.tsv
pyviper/data/translate/human_mouse_gene_translation.csv
viper_in_python-1.1.0.dist-info/licenses/LICENSE
viper_in_python-1.1.0.dist-info/METADATA
viper_in_python-1.1.0.dist-info/WHEEL
viper_in_python-1.1.0.dist-info/top_level.txt
viper_in_python-1.1.0.dist-info/RECORD
