Metadata-Version: 2.4
Name: viper-in-python
Version: 1.1.0
Summary: A package for VIPER-based Protein Activity analysis of transcriptomic data in Python
Home-page: https://github.com/alevax/pyviper
Author: Alexander L.E. Wang & Zizhao Lin & Luca Zanella
Author-email: aw3436@cumc.columbia.edu
License: MIT
Project-URL: Documentation, https://alevax.github.io/pyviper/
Project-URL: Source, https://github.com/alevax/pyviper
Requires-Python: >=3.8
License-File: LICENSE
Requires-Dist: scipy>=1.10.0
Requires-Dist: tqdm
Requires-Dist: scanpy
Requires-Dist: anndata
Requires-Dist: pandas
Requires-Dist: numpy
Requires-Dist: joblib
Requires-Dist: statsmodels
Requires-Dist: loompy
Dynamic: author
Dynamic: author-email
Dynamic: description
Dynamic: description-content-type
Dynamic: home-page
Dynamic: license
Dynamic: license-file
Dynamic: project-url
Dynamic: requires-dist
Dynamic: requires-python
Dynamic: summary
